{
  "name": "Thunderous Smite",
  "level": 1,
  "school": "Evocation",
  "classes": ["Paladin"],
  "ritual": false,
  "castingTime": {
    "type": "BonusAction",
    "ritual": false,
    "trigger": "immediately after hitting a target with a Melee weapon or an Unarmed Strike"
  },
  "range": {
    "type": "Self"
  },
  "components": {
    "verbal": true,
    "somatic": false
  },
  "duration": {
    "type": "Instantaneous",
    "concentration": false
  },
  "description": "Your strike rings with thunder that is audible within 300 feet of you, and the target takes an extra 2d6 Thunder damage from the attack. Additionally, if the target is a creature, it must succeed on a Strength saving throw or be pushed 10 feet away from you and have the Prone condition.",
  "targetType": "creature",
  "damage": [
    {
      "dice": {
        "diceCount": 2,
        "diceValue": 6
      },
      "type": "Thunder",
      "applicationType": "onHit"
    }
  ],
  "savingThrow": {
    "ability": "Strength",
    "noEffectOnSuccess": true,
    "effectOnFailure": "pushed 10 feet away from you and has the Prone condition"
  },
  "conditionsApplied": [
    {
      "condition": "Prone",
      "trigger": "onFailedSave"
    }
  ],
  "forcedMovement": [
    {
      "type": "push",
      "distanceFeet": 10,
      "direction": "away",
      "onFailedSave": true
    }
  ],
  "higherLevelCasting": {
    "scaling": [
      {
        "type": "damageIncrease",
        "diceCountPerLevel": 1,
        "diceValue": 6,
        "baseSpellLevel": 1,
        "description": "The damage increases by 1d6 for each spell slot level above 1."
      }
    ]
  },
  "tags": ["smite", "thunder", "melee", "bonus-action-cast"]
}
