{
  "name": "Action",
  "slug": "action",
  "description": "On each of your turns during combat, you can move and take one action. The Actions table lists the game's main actions.\n\n### Actions\n\n| Action | Summary |\n|---|---|\n| Attack | Attack with a weapon or Unarmed Strike |\n| Dash | For the rest of the turn, give yourself extra movement equal to your Speed |\n| Disengage | Your movement doesn't provoke Opportunity Attacks for the rest of the turn |\n| Dodge | Until the start of your next turn, attack rolls against you have Disadvantage, and you make Dexterity saving throws with Advantage. You lose this benefit if you have the Incapacitated condition or if your Speed is 0 |\n| Help | Help another creature's ability check or attack roll, or administer First Aid |\n| Hide | Make a Dexterity (Stealth) check |\n| Influence | Make a Charisma (Deception, Intimidation, Performance, or Persuasion) or Wisdom (Animal Handling) check to alter a creature's attitude |\n| Magic | Cast a spell, use a magic item, or use a magical feature |\n| Ready | Prepare to take an action in response to a trigger you define |\n| Search | Make a Wisdom (Insight, Medicine, Perception, or Survival) check |\n| Study | Make an Intelligence (Arcana, History, Investigation, Nature, or Religion) check |\n| Utilize | Use a nonmagical object |",
  "category": "Rule",
  "source": {
    "book": "2024 Players Handbook",
    "chapter": "Appendix C",
    "section": "Rules Glossary"
  }
}
